parsons/__init__.py
parsons/actblue/__init__.py
parsons/actblue/actblue.py
parsons/action_builder/__init__.py
parsons/action_builder/action_builder.py
parsons/action_kit/__init__.py
parsons/action_kit/action_kit.py
parsons/action_network/__init__.py
parsons/action_network/action_network.py
parsons/airmeet/__init__.py
parsons/airmeet/airmeet.py
parsons/airtable/__init__.py
parsons/airtable/airtable.py
parsons/alchemer/__init__.py
parsons/alchemer/alchemer.py
parsons/auth0/__init__.py
parsons/auth0/auth0.py
parsons/aws/__init__.py
parsons/aws/aws_async.py
parsons/aws/lambda_distribute.py
parsons/aws/s3.py
parsons/azure/__init__.py
parsons/azure/azure_blob_storage.py
parsons/bill_com/__init__.py
parsons/bill_com/bill_com.py
parsons/bloomerang/__init__.py
parsons/bloomerang/bloomerang.py
parsons/bluelink/__init__.py
parsons/bluelink/bluelink.py
parsons/bluelink/person.py
parsons/box/__init__.py
parsons/box/box.py
parsons/braintree/__init__.py
parsons/braintree/braintree.py
parsons/capitol_canary/__init__.py
parsons/capitol_canary/capitol_canary.py
parsons/catalist/__init__.py
parsons/catalist/catalist.py
parsons/census/__init__.py
parsons/census/census.py
parsons/civis/__init__.py
parsons/civis/civisclient.py
parsons/community/__init__.py
parsons/community/community.py
parsons/controlshift/__init__.py
parsons/controlshift/controlshift.py
parsons/copper/__init__.py
parsons/copper/copper.py
parsons/crowdtangle/__init__.py
parsons/crowdtangle/crowdtangle.py
parsons/databases/__init__.py
parsons/databases/alchemy.py
parsons/databases/database_connector.py
parsons/databases/db_sync.py
parsons/databases/discover_database.py
parsons/databases/table.py
parsons/databases/database/__init__.py
parsons/databases/database/constants.py
parsons/databases/database/database.py
parsons/databases/mysql/__init__.py
parsons/databases/mysql/constants.py
parsons/databases/mysql/create_table.py
parsons/databases/mysql/mysql.py
parsons/databases/postgres/__init__.py
parsons-5.0.0.dist-info/licenses/LICENSE.md
parsons-5.0.0.dist-info/METADATA
parsons-5.0.0.dist-info/WHEEL
parsons-5.0.0.dist-info/top_level.txt
parsons-5.0.0.dist-info/RECORD
