Metadata-Version: 2.4
Name: parsons
Version: 5.0.0
Home-page: https://github.com/move-coop/parsons
Author: The Movement Cooperative
Author-email: info@movementcooperative.org
Keywords: PROGRESSIVE,API,ETL
Classifier: Development Status :: 3 - Alpha
Classifier: Intended Audience :: Developers
Classifier: Programming Language :: Python :: 3.9
Classifier: Programming Language :: Python :: 3.10
Classifier: Programming Language :: Python :: 3.11
Classifier: Programming Language :: Python :: 3.12
Classifier: Programming Language :: Python :: 3.13
Requires-Python: >=3.9,<3.14
License-File: LICENSE.md
Requires-Dist: pyairtable==3.0.2
Requires-Dist: azure-storage-blob==12.25.1
Requires-Dist: boto3>=1.17.98
Requires-Dist: boxsdk==3.14.0
Requires-Dist: braintree==4.31.0
Requires-Dist: bs4==0.0.2
Requires-Dist: censusgeocode==0.5.2
Requires-Dist: civis==1.16.1; python_version < "3.10"
Requires-Dist: civis==2.4.3; python_version >= "3.10"
Requires-Dist: curlify==2.2.1
Requires-Dist: dbt_core>=1.5.0
Requires-Dist: defusedxml<=0.8.0,>=0.7.1
Requires-Dist: facebook-business==22.0.2
Requires-Dist: google-api-core==2.24.2
Requires-Dist: google-api-python-client==2.173.0
Requires-Dist: google-auth==2.38.0
Requires-Dist: google-cloud-bigquery==3.34.0
Requires-Dist: google-cloud-storage-transfer==1.16.0
Requires-Dist: google-cloud-storage==3.1.0
Requires-Dist: grpcio==1.68.1
Requires-Dist: gspread==6.2.1
Requires-Dist: httplib2==0.22.0
Requires-Dist: joblib==1.2.0; python_version < "3.10"
Requires-Dist: joblib==1.4.2; python_version >= "3.10"
Requires-Dist: mysql-connector-python==9.3.0
Requires-Dist: newmode==0.1.6
Requires-Dist: oauth2client==4.1.3
Requires-Dist: paramiko==3.5.1
Requires-Dist: petl==1.7.16
Requires-Dist: psycopg2-binary==2.9.9; python_version < "3.13"
Requires-Dist: psycopg2-binary==2.9.10; python_version >= "3.13"
Requires-Dist: PyGitHub==2.6.0
Requires-Dist: python-dateutil==2.9.0.post0
Requires-Dist: requests==2.32.4
Requires-Dist: requests_oauthlib==2.0.0
Requires-Dist: setuptools==80.9.0
Requires-Dist: simple-salesforce==1.12.6
Requires-Dist: simplejson==3.20.1
Requires-Dist: slackclient==1.3.1
Requires-Dist: sqlalchemy!=1.4.33,<3.0.0,>=1.4.22
Requires-Dist: suds-py3==1.4.5.0
Requires-Dist: surveygizmo==1.2.3
Requires-Dist: twilio==9.6.0
Requires-Dist: urllib3==1.26.19
Requires-Dist: validate-email==1.3
Requires-Dist: xmltodict==0.14.2
Requires-Dist: jinja2>=3.0.2
Requires-Dist: selenium==3.141.0
Requires-Dist: us==3.2.0
Requires-Dist: sshtunnel==0.4.0
Provides-Extra: all
Dynamic: author
Dynamic: author-email
Dynamic: classifier
Dynamic: description
Dynamic: description-content-type
Dynamic: home-page
Dynamic: keywords
Dynamic: license-file
Dynamic: provides-extra
Dynamic: requires-dist
Dynamic: requires-python
